LICENSE
MANIFEST.in
README
setup.cfg
setup.py
examples/NC_009525-NC_002945.coords
examples/NC_009525.fna
examples/nucmer.coords
examples/promer.coords
scaffoldsis/__init__.py
scaffoldsis/multifasta.py
scaffoldsis/sis.py
scaffoldsis.egg-info/PKG-INFO
scaffoldsis.egg-info/SOURCES.txt
scaffoldsis.egg-info/dependency_links.txt
scaffoldsis.egg-info/entry_points.txt
scaffoldsis.egg-info/top_level.txt
tests/__init__.py
tests/context.py
tests/test_sis_package.py