Metadata-Version: 1.1
Name: scaffoldsis
Version: 0.1.2
Summary: genome scaffolder for prokaryotes
Home-page: https://github.com/nickp60/SIS
Author: Nick Waters
Author-email: nickp60@gmail.com
License: MIT
Keywords: bioinformatics
Platform: UNKNOWN
Classifier: Development Status :: 4 - Beta
Classifier: Intended Audience :: Developers
Classifier: Topic :: Software Development :: Build Tools
Classifier: License :: OSI Approved :: MIT License
Classifier: Programming Language :: Python :: 3
